MANIFEST.in
README.rst
VERSION
setup.py
hitchs3/__init__.py
hitchs3/example.jinja2
hitchs3/s3server.py
hitchs3/service.py
hitchs3.egg-info/PKG-INFO
hitchs3.egg-info/SOURCES.txt
hitchs3.egg-info/dependency_links.txt
hitchs3.egg-info/entry_points.txt
hitchs3.egg-info/not-zip-safe
hitchs3.egg-info/requires.txt
hitchs3.egg-info/top_level.txt
hitchs3/templates/list_buckets.jinja2
hitchs3/templates/list_buckets.xml